pyproject/__init__.py
pyproject/__version__.py
pyproject/cli.py
pyproject/licenses.py
pyproject/logger.py
pyproject/project_builder.py
pyproject/spinner.py
pyproject/utils.py
pyproject/config/default_config.json
pyproject/templates/gh_actions_status_update.template
pyproject/templates/gh_actions_tests.template
pyproject/templates/gitignore.template
pyproject/templates/license_agpl_v3.template
pyproject/templates/license_apache_v2.template
pyproject/templates/license_bsd2.template
pyproject/templates/license_bsd3.template
pyproject/templates/license_gpl_v2.template
pyproject/templates/license_gpl_v3.template
pyproject/templates/license_lgpl_v3.template
pyproject/templates/license_mit.template
pyproject/templates/license_mozilla_v2.template
pyproject/templates/pre_commit_config.template
pyproject/templates/pyproject.template
pyproject/templates/readme.template
pyproject/templates/setup.template
pyproject/templates/tox.template
pyproject_generator-0.3.0.dist-info/LICENSE
pyproject_generator-0.3.0.dist-info/METADATA
pyproject_generator-0.3.0.dist-info/WHEEL
pyproject_generator-0.3.0.dist-info/entry_points.txt
pyproject_generator-0.3.0.dist-info/top_level.txt
pyproject_generator-0.3.0.dist-info/RECORD
