Metadata-Version: 2.1
Name: pyproject-generator
Version: 0.3.0
Summary: A command line tool to setup Python packages
Home-page: https://github.com/CangyuanLi/pyproject
Author: Cangyuan Li
Author-email: everest229@gmail.com
License: MIT
Project-URL: Bug Tracker, https://github.com/CangyuanLi/pyproject/issues
Classifier: Programming Language :: Python :: 3
Classifier: License :: OSI Approved :: MIT License
Classifier: Operating System :: OS Independent
Requires-Python: >=3.6
License-File: LICENSE
Requires-Dist: platformdirs
Requires-Dist: rich
